{
  "language": "Marathi",
  "unique_characters": 255,
  "vocabulary_size": 61,
  "vocabulary_percentage": 23.92156862745098,
  "coverage": 0.9516484662985447,
  "vocabulary": [
    "ा",
    "्",
    "र",
    "े",
    "त",
    "य",
    "ी",
    "क",
    "ल",
    "न",
    "स",
    "व",
    "ि",
    "ं",
    "म",
    "ह",
    "च",
    "प",
    "द",
    "ण",
    "ो",
    "आ",
    "ु",
    ".",
    "ज",
    "ग",
    "श",
    "ट",
    "ब",
    "ू",
    "अ",
    "ड",
    "a",
    "ध",
    "ळ",
    "e",
    "ष",
    "भ",
    "ख",
    "ठ",
    "t",
    "i",
    "r",
    "2",
    "0",
    "s",
    "o",
    "n",
    "घ",
    "थ",
    "1",
    "h",
    "ए",
    ":",
    "झ",
    "उ",
    "m",
    "फ",
    "d",
    "l",
    "-"
  ]
}